pyforecho/__init__.py
pyforecho/pyforecho.py
pyforecho/utils.py
pyforecho/api/__init__.py
pyforecho/api/account.py
pyforecho/api/activity_log.py
pyforecho/api/client.py
pyforecho/api/entity.py
pyforecho/api/exceptions.py
pyforecho/api/field.py
pyforecho/api/inbox.py
pyforecho/api/message.py
pyforecho/api/msg_log.py
pyforecho/api/notice.py
pyforecho/api/payment.py
pyforecho/api/product.py
pyforecho/api/project.py
pyforecho/api/report.py
pyforecho/api/sale.py
pyforecho/api/serial.py
pyforecho/api/survey.py
pyforecho/api/transaction.py
pyforecho-0.0.6.dist-info/LICENSE
pyforecho-0.0.6.dist-info/METADATA
pyforecho-0.0.6.dist-info/WHEEL
pyforecho-0.0.6.dist-info/top_level.txt
pyforecho-0.0.6.dist-info/RECORD
