Metadata-Version: 2.1
Name: pyforecho
Version: 0.0.6
Summary: Python wrapper for the Echo Mobile API
Home-page: https://github.com/kelvingakuo/pyforecho
Author: Kelvin Gakuo
Author-email: kelvingakuo@gmail.com
License: UNKNOWN
Platform: UNKNOWN
Classifier: Programming Language :: Python :: 3.5
Classifier: License :: OSI Approved :: MIT License
Classifier: Operating System :: OS Independent
Requires-Python: >3.6.0
Requires-Dist: requests (==2.25.0)
